Instruction_Memory/inst_mem.v
/* 
Instruction memory takes in two inputs: A 32-bit Program counter and a 1-bit reset. 
When reset is set to 0, Based on the value of PC, corresponding 32-bit Instruction code is output
*/
module inst_mem(
    input [31:0] pc,
    input reset,
    output [31:0] inst_code
);
    reg [7:0] Memory [31:0]; // Byte addressable memory with 32 locations
    assign inst_code= {Memory[PC+3],Memory[PC+2],Memory[PC+1],Memory[PC]};

    // Initializing memory when reset is one
    always @(reset)
    begin
        if(reset == 1)
        begin

            // Setting 32-bit instruction: add t1, s0,s1 => 0x00940333 
            Memory[3] = 8'h00;
            Memory[2] = 8'h94;
            Memory[1] = 8'h03;
            Memory[0] = 8'h33;

            // Setting 32-bit instruction: sub t2, s2, s3 => 0x413903b3
            Memory[7] = 8'h41;
            Memory[6] = 8'h39;
            Memory[5] = 8'h03;
            Memory[4] = 8'hb3;

            // Setting 32-bit instruction: mul t0, s4, s5 => 0x035a02b3
            Memory[11] = 8'h03;
            Memory[10] = 8'h5a;
            Memory[9] = 8'h02;
            Memory[8] = 8'hb3;

            // Setting 32-bit instruction: xor t3, s6, s7 => 0x017b4e33
            Memory[15] = 8'h01;
            Memory[14] = 8'h7b;
            Memory[13] = 8'h4e;
            Memory[12] = 8'h33;

            // Setting 32-bit instruction: sll t4, s8, s9 => 0x019c1eb3
            Memory[19] = 8'h01;
            Memory[18] = 8'h9c;
            Memory[17] = 8'h1e;
            Memory[16] = 8'hb3;

            // Setting 32-bit instruction: srl t5, s10, s11 => 0x01bd5f33
            Memory[23] = 8'h01;
            Memory[22] = 8'hbd;
            Memory[21] = 8'h5f;
            Memory[20] = 8'h33;

            // Setting 32-bit instruction: and t6, a2, a3 => 0x00d67fb3
            Memory[27] = 8'h00;
            Memory[26] = 8'hd6;
            Memory[25] = 8'h7f;
            Memory[24] = 8'hb3;

            // Setting 32-bit instruction: or a7, a4, a5 => 0x00f768b3
            Memory[31] = 8'h00;
            Memory[30] = 8'hf7;
            Memory[29] = 8'h68;
            Memory[28] = 8'hb3;
        end
    end

endmodule

inst_fetch_unit.v
`include "inst_mem.v"

module inst_fetch_unit (
    input clk, 
    input reset,
    output reg [31:0] inst_code
);

reg [31:0] pc = 32'b0;

// Declare a wire to connect inst_mem output to the register inst_code
wire [31:0] inst_mem_output;

inst_mem inst_mem_instance(pc, reset, inst_mem_output);

always @(posedge clk or posedge reset) begin
    if (reset == 1'b1)
        pc <= 32'b0;
    else
        pc <= pc + 32'b100; // Increment by 4 (assuming 4-byte instructions)
end

// Assign the value of inst_mem_output to inst_code
always @(*) begin
    inst_code = inst_mem_output;
end

endmodule

alu_defs.v
//ALU operations with their control lines

`define ALU_NONE               4'b0000
`define ALU_SHIFTL             4'b0001
`define ALU_SHIFTR             4'b0010
`define ALU_SHIFTR_ARITH       4'b0011
`define ALU_ADD                4'b0100
`define ALU_SUB                4'b0101
`define ALU_AND                4'b0110
`define ALU_OR                 4'b0111
`define ALU_XOR                4'b1000
`define ALU_LESS_THAN          4'b1001
`define ALU_LESS_THAN_SIGNED   4'b1010

alu.v
`include "alu_defs.v"
module ALU (
    input [31:0] inp1, 
    input [31:0] inp2,
    input [3:0] alu_control,
    output reg [31:0] alu_result,
    output reg zero_flag
);
always @(*) begin
    case(alu_control)
        `ALU_SHIFTL: 
        begin
            if(inp2[0] == 1'b1)
                alu_result = {inp1[30:0],1'b0};
            else if(inp2[1] == 1'b1)
                alu_result = {inp1[29:0],2'b00};
            else if(inp2[2] == 1'b1)
                alu_result = {inp1[27:0],4'b0000};
            else if(inp2[3] == 1'b1)
                alu_result = {inp1[23:0],8'b00000000};
            else if(inp2[4] == 1'b1)
                alu_result = {inp1[15:0],16'b0000000000000000};
            else
                alu_result = inp1;
        end

        `ALU_SHIFTR: //this is the one that does not add the 1 in the MSB
        begin
            if(inp2[0] == 1'b1)
                alu_result = {1'b0,inp1[31:1]};
            else if(inp2[1] == 1'b1)
                alu_result = {2'b00,inp1[31:2]};
            else if(inp2[2] == 1'b1)
                alu_result = {4'b0000,inp1[31:4]};
            else if(inp2[3] == 1'b1)
                alu_result = {8'b00000000,inp1[31:8]};
            else if(inp2[4] == 1'b1)
                alu_result = {16'b0000000000000000,inp1[31:16]};
            else
                alu_result = inp1;
        end

        `ALU_SHIFTR_ARITH: //this is the one that adds the 1 in the MSB
        begin
            if(inp2[0] == 1'b1)
                alu_result = {1'b1,inp1[31:1]};
            else if(inp2[1] == 1'b1)
                alu_result = {2'b11,inp1[31:2]};
            else if(inp2[2] == 1'b1)
                alu_result = {4'b1111,inp1[31:4]};
            else if(inp2[3] == 1'b1)
                alu_result = {8'b11111111,inp1[31:8]};
            else if(inp2[4] == 1'b1)
                alu_result = {16'b1111111111111111,inp1[31:16]};
            else
                alu_result = inp1;
        end
        `ALU_ADD: alu_result = inp1 + inp2;
        `ALU_SUB: alu_result = inp1 - inp2;
        `ALU_AND: alu_result = inp1 & inp2;
        `ALU_OR: alu_result = inp1 | inp2;
        `ALU_XOR: alu_result = inp1 ^ inp2;
        `ALU_LESS_THAN: alu_result = (inp1 < inp2)?32'b1:32'b0;
        `ALU_LESS_THAN_SIGNED: 
        begin
            if (inp1[31] != inp2[31])
                alu_result  = inp1[31] ? 32'h1 : 32'h0;
            else
                alu_result  = (inp1 - inp2) ? 32'h1 : 32'h0;            
        end
         default: alu_result = inp1;

    endcase
    begin
    if(alu_result == 0)
        zero_flag = 1'b1;
    else 
        zero_flag = 1'b0;
    end    
end  
endmodule

register_block.v
// the register block will be a 32 registers each 32 bits wide

// to address all the blocks in 32 registers, we need to have 5 bits for addressing the register block
module register_block(
    input clk,
    input write_on_register,
    input reset,
    input [4:0] read_reg_data_1,
    input [4:0] read_reg_data_2,
    input [4:0] write_reg,
    input [31:0] write_data,
    output [31:0] read_data1,
    output [31:0] read_data2   
);
reg [31:0] reg_memory [31:0];

always@(posedge reset)
begin
    reg_memory[0] = 32'h0;
    reg_memory[1] = 32'h1;
    reg_memory[2] = 32'h2;
    reg_memory[3] = 32'h3;
    reg_memory[4] = 32'h4;
    reg_memory[5] = 32'h5;
    reg_memory[6] = 32'h6;
    reg_memory[7] = 32'h7;
    reg_memory[8] = 32'h8;
    reg_memory[9] = 32'h9;
    reg_memory[10] = 32'h10;
    reg_memory[11] = 32'h11;
    reg_memory[12] = 32'h12;
    reg_memory[13] = 32'h13;
    reg_memory[14] = 32'h14;
    reg_memory[15] = 32'h15;
    reg_memory[16] = 32'h16;
    reg_memory[17] = 32'h17;
    reg_memory[18] = 32'h18;
    reg_memory[19] = 32'h19;
    reg_memory[20] = 32'h20;
    reg_memory[21] = 32'h21;
    reg_memory[22] = 32'h22;
    reg_memory[23] = 32'h23;
    reg_memory[24] = 32'h24;
    reg_memory[25] = 32'h25;
    reg_memory[26] = 32'h26;
    reg_memory[27] = 32'h27;
    reg_memory[28] = 32'h28;
    reg_memory[29] = 32'h29;
    reg_memory[30] = 32'h30;
    reg_memory[31] = 32'h31;
end
assign read_data1 = reg_memory[read_reg_data_1];
assign read_data2 = reg_memory[read_reg_data_2];

always@(posedge clk)
begin
    if(write_on_register)
        begin
            reg_memory[write_reg] = write_data;
        end
end
endmodule

datapath.v
// Implementation of the data flow between the register block and the ALU unit
`include "alu.v"
`include "register_block.v"

module datapath (
    input [4:0] read_reg1,
    input [4:0] read_reg2,
    input [4:0] write_reg,
    input [3:0] alu_control,
    input write_on_register,
    input clk,
    input reset,
    output zero_flag
);
//these wires carry the data
wire [31:0] write_data;
wire [31:0] read_data1;
wire [31:0] read_data2;

register_block register_block_instance(
    clk,
    write_on_register,
    reset,
    read_reg1,
    read_reg2,
    write_reg,
    write_data,
    read_data1,
    read_data2
);
ALU alu_instance(read_data1,read_data2,alu_control,write_data,zero_flag);
    
endmodule

control_block.v
module control_block(
    // the naming and the bits assigned are done in accordance with the base intruction formats
    input [6:0] func7,
    input [2:0] func3,
    input [6:0] opcode,
    output reg [3:0] alu_control,
    output reg write_on_register
);
always@(func7 or func3 or opcode)
begin
    //for all R-type instrcutions, this is the opcode
    // refer the doc for all the values of the parameters
    if(opcode == 7'b011011)
    begin
        case(func3)
            3'b000: begin // func3 == 000
                if (func7 == 7'b0000000) // func7 == 0
                    alu_control = 4'b0100;
                else if (func7 == 7'b1000000) // func7 == 32
                    alu_control = 4'b0101;
            end

            3'b001: alu_control = 4'b0001;
            3'b010: alu_control = 4'b1010;
            3'b011: alu_control = 4'b1001;
            3'b100: alu_control = 4'b1000;
            3'b101: begin // func3 == 101
                if (func7 == 7'b0000000) // func7 == 0
                    alu_control = 4'b0010;
                else if (func7 == 7'b1000000) // func7 == 32
                    alu_control = 4'b0011;
            end

            3'b110: alu_control = 4'b0111;
            3'b111: alu_control = 4'b0110;
        endcase
        
    end
end

    
endmodule

processor.v
`include "control_block.v"
`include "datapath.v"
`include "inst_fetch_unit.v"

module processor(
    input clk,
    input reset,
    output zero_flag
);
wire [31:0] inst_code;
wire [3:0] alu_control;
wire write_on_register;

control_block control_block_instance(inst_code[31:25],inst_code[14:12],inst_code[6:0],alu_control,write_on_register);
datapath datapath_instance(inst_code[19:15], inst_code[24:20], inst_code[11:7], alu_control, write_on_register, clk, reset, zero_flag);
inst_fetch_unit inst_fetch_unit_instance(clk,reset,inst_code);

    
endmodule

processor_tb.v
`include "processor.v"

module processor_tb ();
    reg clk;
    reg reset;
    wire zero_flag;

    processor processor_instance(clk,reset,zero_flag);

    initial 
    begin
        $dumpfile("output_wave.vcd");
        $dumpvars(0,processor_instance);        
    end

    initial
    begin
        clk = 0;
        forever 
        begin
            #20 clk = ~clk;            
        end
    end

    initial
    begin
        reset = 1;
        #50 reset = 0;
    end
    
    initial
    #300 $finish;
endmodule

output_wave.vcd
$date
	Mon May 20 19:49:48 2024
$end
$version
	Icarus Verilog
$end
$timescale
	1s
$end
$scope module processor_tb $end
$scope module processor_instance $end
$var wire 1 ! clk $end
$var wire 1 " reset $end
$var wire 1 # zero_flag $end
$var wire 1 $ write_on_register $end
$var wire 32 % inst_code [31:0] $end
$var wire 4 & alu_control [3:0] $end
$scope module control_block_instance $end
$var wire 3 ' func3 [2:0] $end
$var wire 7 ( func7 [6:0] $end
$var wire 7 ) opcode [6:0] $end
$var reg 4 * alu_control [3:0] $end
$var reg 1 $ write_on_register $end
$upscope $end
$scope module datapath_instance $end
$var wire 4 + alu_control [3:0] $end
$var wire 1 ! clk $end
$var wire 5 , read_reg1 [4:0] $end
$var wire 5 - read_reg2 [4:0] $end
$var wire 1 " reset $end
$var wire 1 $ write_on_register $end
$var wire 5 . write_reg [4:0] $end
$var wire 1 # zero_flag $end
$var wire 32 / write_data [31:0] $end
$var wire 32 0 read_data2 [31:0] $end
$var wire 32 1 read_data1 [31:0] $end
$scope module alu_instance $end
$var wire 4 2 alu_control [3:0] $end
$var wire 32 3 inp2 [31:0] $end
$var wire 32 4 inp1 [31:0] $end
$var reg 32 5 alu_result [31:0] $end
$var reg 1 # zero_flag $end
$upscope $end
$scope module register_block_instance $end
$var wire 1 ! clk $end
$var wire 32 6 read_data1 [31:0] $end
$var wire 32 7 read_data2 [31:0] $end
$var wire 5 8 read_reg_data_1 [4:0] $end
$var wire 5 9 read_reg_data_2 [4:0] $end
$var wire 1 " reset $end
$var wire 32 : write_data [31:0] $end
$var wire 1 $ write_on_register $end
$var wire 5 ; write_reg [4:0] $end
$upscope $end
$upscope $end
$scope module inst_fetch_unit_instance $end
$var wire 1 ! clk $end
$var wire 1 " reset $end
$var wire 32 < inst_mem_output [31:0] $end
$var reg 32 = inst_code [31:0] $end
$var reg 32 > pc [31:0] $end
$scope module inst_mem_instance $end
$var wire 32 ? pc [31:0] $end
$var wire 1 " reset $end
$var wire 32 @ inst_code [31:0] $end
$upscope $end
$upscope $end
$upscope $end
$upscope $end
$enddefinitions $end
$comment Show the parameter values. $end
$dumpall
$end
#0
$dumpvars
b100101000000001100110011 @
b0 ?
b0 >
b100101000000001100110011 =
b100101000000001100110011 <
b110 ;
b1000 :
b1001 9
b1000 8
b1001 7
b1000 6
b1000 5
b1000 4
b1001 3
bx 2
b1000 1
b1001 0
b1000 /
b110 .
b1001 -
b1000 ,
bx +
bx *
b110011 )
b0 (
b0 '
bx &
b100101000000001100110011 %
x$
0#
1"
0!
$end
#20
1!
#40
0!
#50
0"
#60
b11000 /
b11000 5
b11000 :
b111 .
b111 ;
b11001 0
b11001 3
b11001 7
b10011 -
b10011 9
b11000 1
b11000 4
b11000 6
b10010 ,
b10010 8
b100000 (
b1000001001110010000001110110011 %
b1000001001110010000001110110011 =
b1000001001110010000001110110011 <
b1000001001110010000001110110011 @
b100 >
b100 ?
1!
#80
0!
#100
b100000 /
b100000 5
b100000 :
b101 .
b101 ;
b100001 0
b100001 3
b100001 7
b10101 -
b10101 9
b100000 1
b100000 4
b100000 6
b10100 ,
b10100 8
b1 (
b11010110100000001010110011 %
b11010110100000001010110011 =
b11010110100000001010110011 <
b11010110100000001010110011 @
b1000 >
b1000 ?
1!
#120
0!
#140
b100010 /
b100010 5
b100010 :
b11100 .
b11100 ;
b100011 0
b100011 3
b100011 7
b10111 -
b10111 9
b100010 1
b100010 4
b100010 6
b10110 ,
b10110 8
b100 '
b0 (
b1011110110100111000110011 %
b1011110110100111000110011 =
b1011110110100111000110011 <
b1011110110100111000110011 @
b1100 >
b1100 ?
1!
#160
0!
#180
b100100 /
b100100 5
b100100 :
b11101 .
b11101 ;
b100101 0
b100101 3
b100101 7
b11001 -
b11001 9
b100100 1
b100100 4
b100100 6
b11000 ,
b11000 8
b1 '
b1100111000001111010110011 %
b1100111000001111010110011 =
b1100111000001111010110011 <
b1100111000001111010110011 @
b10000 >
b10000 ?
1!
#200
0!
#220
b100110 /
b100110 5
b100110 :
b11110 .
b11110 ;
b100111 0
b100111 3
b100111 7
b11011 -
b11011 9
b100110 1
b100110 4
b100110 6
b11010 ,
b11010 8
b101 '
b1101111010101111100110011 %
b1101111010101111100110011 =
b1101111010101111100110011 <
b1101111010101111100110011 @
b10100 >
b10100 ?
1!
#240
0!
#260
b10010 /
b10010 5
b10010 :
b11111 .
b11111 ;
b10011 0
b10011 3
b10011 7
b1101 -
b1101 9
b10010 1
b10010 4
b10010 6
b1100 ,
b1100 8
b111 '
b110101100111111110110011 %
b110101100111111110110011 =
b110101100111111110110011 <
b110101100111111110110011 @
b11000 >
b11000 ?
1!
#280
0!
#300
b10100 /
b10100 5
b10100 :
b10001 .
b10001 ;
b10101 0
b10101 3
b10101 7
b1111 -
b1111 9
b10100 1
b10100 4
b10100 6
b1110 ,
b1110 8
b110 '
b111101110110100010110011 %
b111101110110100010110011 =
b111101110110100010110011 <
b111101110110100010110011 @
b11100 >
b11100 ?
1!
